{
  "success": true,
  "data": {
    "errCode": 0,
    "errMsg": "执行成功",
    "data": [
      {
        "_id": "c8872b64687f0b32003b0c5560c22bb0",
        "course_id": 3,
        "id": 38200862,
        "seq": 1,
        "test_id": "area_15_03",
        "type": 1,
        "area": 15,
        "tigan": "某系统集成项目制定风险管理计划时，发现病毒入侵有可能导致服务器死机或不能访问，此风险属于（）。【20下】",
        "A": "市场风险",
        "B": "经营风险",
        "C": "技术风险",
        "D": "设备风险",
        "answer": "C",
        "explanation": "病毒肯定属于技术类",
        "tigan_pic": "",
        "explanation_pic": "",
        "done_count": 128,
        "correct_count": 97,
        "correct_prob": 75.8,
        "fav_count": 12,
        "sim_questions": ""
      },
      {
        "_id": "c8872b64687f0b32003b0c602fd88ab9",
        "course_id": 3,
        "id": 39337266,
        "seq": 2,
        "test_id": "area_15_03",
        "type": 1,
        "area": 15,
        "tigan": "关于项目风险的描述，不正确的是（）。【19上】",
        "A": "已知风险与未知风险都可以进行管理",
        "B": "风险既有可能对项目产生正面的影响，也有可能产生负面的影响",
        "C": "同样的风险对于不同的主体有不同的影响",
        "D": "收益越大，人们愿意承担的风险也就越大",
        "answer": "A",
        "explanation": "P431，未知风险是未识别风险，无法管理。",
        "tigan_pic": "",
        "explanation_pic": "",
        "done_count": 128,
        "correct_count": 118,
        "correct_prob": 92.2,
        "fav_count": 7,
        "sim_questions": ""
      },
      {
        "_id": "c8872b64687f0b32003b0c7525a31883",
        "course_id": 3,
        "id": 39452002,
        "seq": 3,
        "test_id": "area_15_03",
        "type": 1,
        "area": 15,
        "tigan": "风险可以从不同角度、根据不同的标准来进行分类。百年不遇的暴雨属于（）；【17下】",
        "A": "不可预测风险",
        "B": "可预测风险",
        "C": "已知风险",
        "D": "技术风险",
        "answer": "A",
        "explanation": "P434，风险可以分为已知风险、可预测风险和不可预测风险：\n①已知风险就是在认真、严格地分析项目及其计划之后就能够明确的那些经常发生的，而且其后果亦可预见的风险。例：项目目标不明确，过分乐观的进度计划，设计或施工变更，材料价格波动等。\n②可预测风险就是根据经验，可以预见其发生，但不可预见其后果的风险。例如：业主不能及时审查批准，分包商不能及时交工，施工机械出现故障，不可预见的地质条件等。\n③不可预测风险就是有可能发生，但其发生的可能性即使最有经验的人亦不能预见的风险。例如地震、百年不遇的暴雨、通货膨胀、政策变化等。",
        "tigan_pic": "",
        "explanation_pic": "",
        "done_count": 130,
        "correct_count": 129,
        "correct_prob": 99.2,
        "fav_count": 2,
        "sim_questions": ""
      },
      {
        "_id": "c8872b64687f0b32003b0c5071e67530",
        "course_id": 3,
        "id": 30648472,
        "seq": 4,
        "test_id": "area_15_03",
        "type": 1,
        "area": 15,
        "tigan": "保证项目决策是在整体项目风险和单个项目风险当前信息的基础上进行，是（）过程的主要作用。",
        "A": "规划风险管理",
        "B": "规划风险应对",
        "C": "实施风险应对",
        "D": "监督风险",
        "answer": "D",
        "explanation": "规划风险管理作用：确保风险管理的水平、方法和可见度与项目风险程度相匹配，与对组织和其他干系人的重要程度相匹配。\n识别风险作用：识别风险是识别单个项目风险以及整体项目风险的来源，并记录风险特征的过程。\n实施定性风险分析作用：实施定性风险分析是通过评估单个项目风险发生的概率和影响及其他特征，对风险进行优先级排序，从而为后续分析或行动提供基础的过程。\n实施定量风险分析作用：实施定量风险分析是就已识别的单个项目风险和不确定性的其他来源对整体项目且标的影响进行定量分析的过程。\n规划风险应对作用：规划风险的应对措施是为了应对项目风险，而制定可选方案、选择应对策略并商定应对行动的过程。\n实施风险应对作用：实施风险应对是执行商定的风险应对计划的过程。\n监督风险作用：监督风险是在整个项目期间，监督风险应对计划的实施，并跟踪已识别风险、识别和分析新风险，以及评估风险管理有效性的过程。",
        "tigan_pic": "",
        "explanation_pic": "",
        "done_count": 125,
        "correct_count": 56,
        "correct_prob": 44.8,
        "fav_count": 43,
        "sim_questions": ""
      },
      {
        "_id": "c8872b64687f0b32003b0c4b6be9fc61",
        "course_id": 3,
        "id": 35103265,
        "seq": 5,
        "test_id": "area_15_03",
        "type": 1,
        "area": 15,
        "tigan": "项目风险管理计划不包含的内容是（）。【16下】",
        "A": "方法论",
        "B": "概率和影响矩阵",
        "C": "风险类别",
        "D": "如何审计风险管理过程",
        "answer": "D",
        "explanation": "P440，风险管理计划内容：①风险管理策略；②方法论；③角色与职责；④资金；⑤时间安排；⑥风险类别；⑦干系人风险偏好；⑧风险概率和影响；⑨概率和影响矩阵；⑩报告格式；（11）跟踪",
        "tigan_pic": "",
        "explanation_pic": "",
        "done_count": 123,
        "correct_count": 51,
        "correct_prob": 41.5,
        "fav_count": 36,
        "sim_questions": ""
      },
      {
        "_id": "c8872b64687f0b32003b0c5a0b238e79",
        "course_id": 3,
        "id": 34288106,
        "seq": 6,
        "test_id": "area_15_03",
        "type": 1,
        "area": 15,
        "tigan": "（）不属于“识别风险”过程的输入。",
        "A": "潜在风险应对措施清单",
        "B": "范围基准",
        "C": "风险管理计划",
        "D": "质量管理计划",
        "answer": "A",
        "explanation": "P444，风险识别的输入：项目管理计划（需求管理计划、进度管理计划、成本管理计划、质量管理计划、资源管理计划、风险管理计划、范围基准、进度基准、成本基准）、项目文件（假设日志、干系人登记册、需求文件、持续时间估算、成本估算、资源需求、问题日志、经验教训登记表）、采购文档、协议、事业环境因素、组织过程资产。潜在风险应对措施清单是识别风险的输出。",
        "tigan_pic": "",
        "explanation_pic": "",
        "done_count": 129,
        "correct_count": 117,
        "correct_prob": 90.7,
        "fav_count": 10,
        "sim_questions": ""
      },
      {
        "_id": "c8872b64687f0b32003b0c4a1c29f72b",
        "course_id": 3,
        "id": 37083277,
        "seq": 7,
        "test_id": "area_15_03",
        "type": 1,
        "area": 15,
        "tigan": "（）不属于定性风险分析的技术。【20下】",
        "A": "风险数据质量评估",
        "B": "概率和影响矩阵",
        "C": "风险紧迫性评估",
        "D": "预期货币价值分析",
        "answer": "D",
        "explanation": "P449，定性风险分析的技术：1．专家判断；2．数据收集（访谈）；3．数据分析（风险数据质量评估、风险概率和影响评估、其他风险参数评估）；4．人际关系与团队技能（引导）；5．风险分类；6．数据表现（概率和影响矩阵、层级图）；7．会议",
        "tigan_pic": "",
        "explanation_pic": "",
        "done_count": 129,
        "correct_count": 102,
        "correct_prob": 79.1,
        "fav_count": 9,
        "sim_questions": ""
      },
      {
        "_id": "c8872b64687f0b32003b0c4c4a5c7da9",
        "course_id": 3,
        "id": 31873341,
        "seq": 8,
        "test_id": "area_15_03",
        "type": 1,
        "area": 15,
        "tigan": "关于风险分析的技术，不正确的是（）。【23上】",
        "A": "概率影响矩阵适用于两个以上的参数对风险进行分类的情况",
        "B": "蒙特卡洛分析，是使用模型模拟大量单个项目风险和其他不确定性来源的综合影响，以评估它们对项目目标的潜在影响",
        "C": "敏感性分析，是将项目结果变化与定量风险分析模型中的要素变化之间建立联系的方法",
        "D": "影响图是不确定条件下进行决策的图形辅助工具",
        "answer": "A",
        "explanation": "P451，层级图：如果使用了两个以上的参数对风险进行分类，那就不能使用概率和影响矩阵，而需要使用其他图形。",
        "tigan_pic": "",
        "explanation_pic": "",
        "done_count": 127,
        "correct_count": 82,
        "correct_prob": 64.6,
        "fav_count": 29,
        "sim_questions": ""
      },
      {
        "_id": "c8872b64687f0b32003b0c816958493a",
        "course_id": 3,
        "id": 31010402,
        "seq": 9,
        "test_id": "area_15_03",
        "type": 1,
        "area": 15,
        "tigan": "敏感性分析的结果通常用（）来表示。【23下2批】",
        "A": "气泡图",
        "B": "龙卷风图",
        "C": "SWOT",
        "D": "概率影响矩阵",
        "answer": "B",
        "explanation": "P455，敏感性分析的结果通常用龙卷风图来表示。",
        "tigan_pic": "",
        "explanation_pic": "",
        "done_count": 130,
        "correct_count": 91,
        "correct_prob": 70,
        "fav_count": 20,
        "sim_questions": ""
      },
      {
        "_id": "c8872b64687f0b32003b0c5434eab82e",
        "course_id": 3,
        "id": 33800796,
        "seq": 10,
        "test_id": "area_15_03",
        "type": 1,
        "area": 15,
        "tigan": "一件商品卖出去将盈利50元，卖不出去将亏损60元，卖出去的概率是80％，卖不出去概率是20％，该商品的预期货币价值（EMV）是（）元。【23上】",
        "A": 6,
        "B": 8,
        "C": 66,
        "D": 28,
        "answer": "D",
        "explanation": "P456，          EMV==50* 80%-60* 20%=28元",
        "tigan_pic": "",
        "explanation_pic": "",
        "done_count": 126,
        "correct_count": 123,
        "correct_prob": 97.6,
        "fav_count": 4,
        "sim_questions": ""
      },
      {
        "_id": "c8872b64687f0b32003b0c4d09917dc7",
        "course_id": 3,
        "id": 30487298,
        "seq": 11,
        "test_id": "area_15_03",
        "type": 1,
        "area": 15,
        "tigan": "用计算机软件数千次迭代运行定量风险分析模型。每次运行，都要随机选择输入值（如成本估算、持续时间估算或概率分支发生频率是（）。",
        "A": "蒙特卡洛分析",
        "B": "敏感性分析",
        "C": "决策树分析",
        "D": "概率和影响矩阵",
        "answer": "A",
        "explanation": "P455，对成本风险进行蒙特卡洛分析时，使用项目成本估算作为模拟的输入；对进度风险进行蒙特卡洛分析时，使用进度网络图和持续时间估算作为模拟的揄入；开展定量成本和进度综合风险分析时，同时使用以上两种输入。其输出就是定量风险分析模型。\n用计算机软件数千次迭代运行定量风险分析模型。每次运行，都要随机选择输入值（如成本估算、持续时间估算或概率分支发生频率）。",
        "tigan_pic": "",
        "explanation_pic": "",
        "done_count": 128,
        "correct_count": 112,
        "correct_prob": 87.5,
        "fav_count": 11,
        "sim_questions": ""
      },
      {
        "_id": "c8872b64687f0b32003b0c5660d4e39c",
        "course_id": 3,
        "id": 37107866,
        "seq": 12,
        "test_id": "area_15_03",
        "type": 1,
        "area": 15,
        "tigan": "项目经理为了回避论文课被某机构抄袭所带来的风险，按计划换一个项目素材来讲课。但是由于时间紧迫，新素材大家理解不深，写出来的质量没有之前的好，这个属于（）。",
        "A": "纯粹风险",
        "B": "投机风险",
        "C": "人为风险",
        "D": "次生风险",
        "answer": "D",
        "explanation": "P458，次生风险是实施风险应对措施直接导致的风险",
        "tigan_pic": "",
        "explanation_pic": "",
        "done_count": 132,
        "correct_count": 103,
        "correct_prob": 78,
        "fav_count": 18,
        "sim_questions": ""
      },
      {
        "_id": "c8872b64687f0b32003b0c6647fd7e29",
        "course_id": 3,
        "id": 36933258,
        "seq": 13,
        "test_id": "area_15_03",
        "type": 1,
        "area": 15,
        "tigan": "A 公司刚刚中标一个大型系统集成项目，其中一台设备计划从国外采购，近期汇率波动明品，A公司准备与客户协商使用国产设备进行替代，这是采用了（）风险应对策略。【18下】",
        "A": "回避",
        "B": "转移",
        "C": "减轻",
        "D": "接受",
        "answer": "A",
        "explanation": "P460，很明显属于回避，规避风险",
        "tigan_pic": "",
        "explanation_pic": "",
        "done_count": 132,
        "correct_count": 98,
        "correct_prob": 74.2,
        "fav_count": 21,
        "sim_questions": ""
      },
      {
        "_id": "c8872b64687f0b32003b0c52348f7832",
        "course_id": 3,
        "id": 32171423,
        "seq": 14,
        "test_id": "area_15_03",
        "type": 1,
        "area": 15,
        "tigan": "下面（）属于工作绩效报告的内容。",
        "A": "已实施的风险应对措施",
        "B": "已发生的风险",
        "C": "偏差分析结果",
        "D": "仍活跃及已关闭的风险",
        "answer": "C",
        "explanation": "P467，工作绩效数据包含关于项目状态的信息，例如，已实施的风险应对措施、已发生的风险、仍活跃及已关闭的风险。\n工作绩效报告通过分析绩效测量结果得出，能够提供关于项目工作绩效的信息，包括偏差分析结果、挣值数据和预测数据。",
        "tigan_pic": "",
        "explanation_pic": "",
        "done_count": 125,
        "correct_count": 76,
        "correct_prob": 60.8,
        "fav_count": 25,
        "sim_questions": ""
      },
      {
        "_id": "c8872b64687f0b32003b0c82081fb18e",
        "course_id": 3,
        "id": 33453406,
        "seq": 15,
        "test_id": "area_15_03",
        "type": 1,
        "area": 15,
        "tigan": "关于风险的描述，正确的是（）。【22上】",
        "A": "风险审计可以在日常项目审查中进行，也可以单独召开风险审计会议",
        "B": "蒙特卡洛分析有助于确定哪些风险对项目具有最大的潜在影响",
        "C": "制定有效的风险应对策略需要风险量化分析",
        "D": "建立应急储备，安排资金和资源应对风险是常见的规避风险策略",
        "answer": "A",
        "explanation": "P467，风险审计是检查并记录风险应对措施在处理已识别风险及其根源方面的有效性，以及风险管理过程的有效性。项目经理要确保按项目风险管理计划所规定的频率实施风险审计。既可以在日常的项目审查会中进行风险审计，也可单独召开风险审计会议。所以A正确\n敏感性分析有助于确定哪些风险对项目具有最大的潜在影响。所以B错误；定量风险分析一般在定性风险分析之后进行，但是，经验丰富的风险经理有时在风险分析过程之后径直进行定量分析。有时，制定有效的风险应对策略并不需要风险量化分析。所以C错误；制定备用策略是在被选策略被证明无效或接受的风险发生时实施。通常，要为时间或成本分配应急储备金。最后，可制订应急计划并识别应急计划实施的触发条件。所以D错误；",
        "tigan_pic": "",
        "explanation_pic": "",
        "done_count": 124,
        "correct_count": 85,
        "correct_prob": 68.5,
        "fav_count": 24,
        "sim_questions": ""
      },
      {
        "_id": "c8872b64687f0b32003b0c612238435d",
        "course_id": 3,
        "id": 38158541,
        "seq": 16,
        "test_id": "area_15_03",
        "type": 1,
        "area": 15,
        "tigan": "关于项目风险的描述，不正确的是（）。",
        "A": "风险具有随机性、相对性、可变性",
        "B": "项目收益越大，人们愿意承担的风险越大",
        "C": "项目投入越多，人们愿意承担的风险越大",
        "D": "风险按照影响范围可分为局部风险和总体风险",
        "answer": "C",
        "explanation": "P432，对于项目风险，人们的承受能力主要受下列几个因素的影响：\n①收益的大小。收益总是有损失的可能性相伴随。损失的可能性和数额越大，人们希望为弥补损失而得到的收益也越大。反过来，收益越大，人们愿意承担的风险也就越大。\n②投入的大小。项目活动投入的越多，人们对成功所抱的希望也越大，愿意冒的风险也就越小。\n③项目活动主体的地位和拥有的资源。管理人员中级别高的同级别低的相比，能够承担大的风\n险。同一风险，不同的个人或组织承受能力也不同。个人或组织拥有的资源越多，其风险承受能力也越大。",
        "tigan_pic": "",
        "explanation_pic": "",
        "done_count": 126,
        "correct_count": 122,
        "correct_prob": 96.8,
        "fav_count": 3,
        "sim_questions": ""
      },
      {
        "_id": "c8872b64687f0b32003b0c691e0f450d",
        "course_id": 3,
        "id": 38400976,
        "seq": 17,
        "test_id": "area_15_03",
        "type": 1,
        "area": 15,
        "tigan": "项目风险管理计划不包含的内容是（）。",
        "A": "风险管理策略",
        "B": "风险登记册",
        "C": "风险类别",
        "D": "时间安排",
        "answer": "B",
        "explanation": "P440，风险管理计划内容：①风险管理策略；②方法论；③角色与职责；④资金；⑤时间安排；⑥风险类别；⑦干系人风险偏好；⑧风险概率和影响；⑨概率和影响矩阵；⑩报告格式；⑪跟踪",
        "tigan_pic": "",
        "explanation_pic": "",
        "done_count": 127,
        "correct_count": 82,
        "correct_prob": 64.6,
        "fav_count": 18,
        "sim_questions": ""
      },
      {
        "_id": "c8872b64687f0b32003b0c6f5967ffd2",
        "course_id": 3,
        "id": 30662938,
        "seq": 18,
        "test_id": "area_15_03",
        "type": 1,
        "area": 15,
        "tigan": "关于风险识别的描述，（）是不正确的。",
        "A": "应采用适合项目的风险描述格式来描述和记录项目风险，以确保每一项风险都被清楚、明确地理解，从而为有效的分析和风险应对措施制定提供支持",
        "B": "应鼓励所有项目干系人参与项目风险的识别工作",
        "C": "风险报告提供关于整体项目风险的信息，以及关于已识别的单个项目风险的概述信息",
        "D": "识别风险是一个迭代的过程。迭代的频率和每次迭代所需的参与程度因情况而异，应在风险管理计划中做出相应规定",
        "answer": "A",
        "explanation": "P443，应采用统一的风险描述格式来描述和记录项目风险，以确保每一项风险都被清楚、明确地理解，从而为有效的分析和风险应对措施制定提供支持。",
        "tigan_pic": "",
        "explanation_pic": "",
        "done_count": 127,
        "correct_count": 78,
        "correct_prob": 61.4,
        "fav_count": 24,
        "sim_questions": ""
      },
      {
        "_id": "c8872b64687f0b32003b0c705f5563ed",
        "course_id": 3,
        "id": 32439885,
        "seq": 19,
        "test_id": "area_15_03",
        "type": 1,
        "area": 15,
        "tigan": "（）评估旨在评价关于单个项目风险的数据的准确性和可靠性。使用低质量的风险数据，可能导致定性风险分析对项目来说基本没用。",
        "A": "定量风险分析",
        "B": "风险概率和影响评估",
        "C": "风险紧迫性评估",
        "D": "风险数据质量评估",
        "answer": "D",
        "explanation": "P449，风险数据质量评估旨在评价关于单个项目风险的数据的准确性和可靠性。使用低质量的风险数据，可能导致定性风险分析对项目来说基本没用。如果数据质量不可接受，就可能需要收集更好的数据。可以开展问卷调查，了解项目干系人对数据质量各方面的评价，包括数据的完整性、客观性、相关性和及时性，进而对风险数据的质量进行综合评估。可以计算这些方面的加权平均数，将其作为数据质量的总体分数。",
        "tigan_pic": "",
        "explanation_pic": "",
        "done_count": 131,
        "correct_count": 113,
        "correct_prob": 86.3,
        "fav_count": 10,
        "sim_questions": ""
      },
      {
        "_id": "c8872b64687f0b32003b0c8315744480",
        "course_id": 3,
        "id": 31199172,
        "seq": 20,
        "test_id": "area_15_03",
        "type": 1,
        "area": 15,
        "tigan": "（）风险在多长时间后会影响一项或多项项目目标。",
        "A": "紧迫性",
        "B": "潜伏性",
        "C": "临近性",
        "D": "可控性",
        "answer": "C",
        "explanation": "P450，邻近性：风险在多长时间后会影响一项或多项项目目标。时间短就说明邻近性高。",
        "tigan_pic": "",
        "explanation_pic": "",
        "done_count": 131,
        "correct_count": 88,
        "correct_prob": 67.2,
        "fav_count": 15,
        "sim_questions": ""
      },
      {
        "_id": "c8872b64687f0b32003b0c62316288c4",
        "course_id": 3,
        "id": 37898734,
        "seq": 21,
        "test_id": "area_15_03",
        "type": 1,
        "area": 15,
        "tigan": "（）不属于风险识别的依据。",
        "A": "成本管理计划",
        "B": "范围基准",
        "C": "采购文件",
        "D": "风险登记册",
        "answer": "D",
        "explanation": "P444，风险识别的输入：项目管理计划（需求管理计划、进度管理计划、成本管理计划、质量管理计划、资源管理计划、风险管理计划、范围基准、进度基准、成本基准）、项目文件（假设日志、干系人登记册、需求文件、持续时间估算、成本估算、资源需求、问题日志、经验教训登记表）、采购文档、协议、事业环境因素、组织过程资产",
        "tigan_pic": "",
        "explanation_pic": "",
        "done_count": 124,
        "correct_count": 107,
        "correct_prob": 86.3,
        "fav_count": 8,
        "sim_questions": ""
      },
      {
        "_id": "c8872b64687f0b32003b0c8442dcf49a",
        "course_id": 3,
        "id": 30407276,
        "seq": 22,
        "test_id": "area_15_03",
        "type": 1,
        "area": 15,
        "tigan": "A公司刚刚中标一个大型系统集成项目，其中一台设备计划从国外采购，近期汇率波动明显，A公司准备与客户协商使用国产设备进行替代，这是采用了（）风险应对策略。",
        "A": "规避",
        "B": "转移",
        "C": "减轻",
        "D": "接受",
        "answer": "A",
        "explanation": "P460，规避。风险规避是指项目团队采取行动来消除威胁，或保护项目免受威胁的影响。它可能适用于发生概率较高，且具有严重负面影响的高优先级的威胁。规避策略可能涉及变更项目管理计划的某些方面，或改变会受负面影响的目标，以便于彻底消除威胁，将它的发生概率降低到零。",
        "tigan_pic": "",
        "explanation_pic": "",
        "done_count": 127,
        "correct_count": 90,
        "correct_prob": 70.9,
        "fav_count": 10,
        "sim_questions": ""
      },
      {
        "_id": "c8872b64687f0b32003b0c4944d3815a",
        "course_id": 3,
        "id": 37070931,
        "seq": 23,
        "test_id": "area_15_03",
        "type": 1,
        "area": 15,
        "tigan": "关于风险识别的描述，不正确的是（）。",
        "A": "应鼓励所有项目人员参与风险的识别",
        "B": "风险登记册的编制始于风险识别过程",
        "C": "并非所有项目都需要实施定量风险分析",
        "D": "识别风险是在项目计划阶段的工作，在其他阶段不涉及",
        "answer": "D",
        "explanation": "P443，在整个项目生命周期中，单个项目风险可能随项目进展而不断变化，整体项目风险的级别也会发生变化。因此，识别风险是一个迭代的过程。",
        "tigan_pic": "",
        "explanation_pic": "",
        "done_count": 128,
        "correct_count": 126,
        "correct_prob": 98.4,
        "fav_count": 4,
        "sim_questions": ""
      },
      {
        "_id": "c8872b64687f0b32003b0c5b74c392c7",
        "course_id": 3,
        "id": 31736400,
        "seq": 24,
        "test_id": "area_15_03",
        "type": 1,
        "area": 15,
        "tigan": "关于风险识别的描述，不正确的是（）。",
        "A": "应鼓励所有项目参与人员识别风险",
        "B": "风险登记册的内容可能包括潜在应对措施清单",
        "C": "可以跳过定量风险分析",
        "D": "识别风险是一次性工作",
        "answer": "D",
        "explanation": "P443，在整个项目生命周期中，单个项目风险可能随项目进展而不断变化，整体项目风险的级别也会发生变化。因此，识别风险是一个迭代的过程。",
        "tigan_pic": "",
        "explanation_pic": "",
        "done_count": 123,
        "correct_count": 122,
        "correct_prob": 99.2,
        "fav_count": 2,
        "sim_questions": ""
      },
      {
        "_id": "c8872b64687f0b32003b0c67008404ff",
        "course_id": 3,
        "id": 38917444,
        "seq": 25,
        "test_id": "area_15_03",
        "type": 1,
        "area": 15,
        "tigan": "（）不属于识别风险过程的成果。",
        "A": "已识别风险清单",
        "B": "潜在应对措施清单",
        "C": "潜在风险责任人",
        "D": "风险描述格式和模板",
        "answer": "D",
        "explanation": "P447，识别风险输出：风险登记册（已识别风险的清单、潜在风险责任人、潜在风险应对措施清单）、风险报告（整体项目风险的来源、关于已识别单个项目风险的概述信息）、项目文件更新（假设条件、问题日志、经验教训登记册）",
        "tigan_pic": "",
        "explanation_pic": "",
        "done_count": 120,
        "correct_count": 106,
        "correct_prob": 88.3,
        "fav_count": 9,
        "sim_questions": ""
      },
      {
        "_id": "c8872b64687f0b32003b0c574140c67d",
        "course_id": 3,
        "id": 34870375,
        "seq": 26,
        "test_id": "area_15_03",
        "type": 1,
        "area": 15,
        "tigan": "关于风险的描述，不正确的是（）。",
        "A": "项目风险是一种不确定的事件或条件",
        "B": "项目风险既包括对项目目标的威胁，也包括促进项目目标的机会",
        "C": "风险是零和游戏，有风险受益者，同时也有风险受害者",
        "D": "在项目中应规避投机风险向纯粹风险的转化",
        "answer": "C",
        "explanation": "P433，风险不是零和游戏，请多情况下风险的各有关方面都要蒙受损失，无一幸免。",
        "tigan_pic": "",
        "explanation_pic": "",
        "done_count": 131,
        "correct_count": 118,
        "correct_prob": 90.1,
        "fav_count": 6,
        "sim_questions": ""
      },
      {
        "_id": "c8872b64687f0b32003b0c7142e1ec55",
        "course_id": 3,
        "id": 35485399,
        "seq": 27,
        "test_id": "area_15_03",
        "type": 1,
        "area": 15,
        "tigan": "（）是关于可能引发项目风险来源的风险类别的预设清单。",
        "A": "头脑风暴",
        "B": "提示清单",
        "C": "根本原因识别",
        "D": "专家访谈",
        "answer": "B",
        "explanation": "P446，提示清单是关于可能引发项目风险来源的风险类别的预设清单。在采用风险识别技术时，提示清单可作为框架用于协助项目团队形成想法。可以用风险分解结构底层的风险类别作为提示清单，来识别单个项目风险。",
        "tigan_pic": "",
        "explanation_pic": "",
        "done_count": 126,
        "correct_count": 121,
        "correct_prob": 96,
        "fav_count": 9,
        "sim_questions": ""
      },
      {
        "_id": "c8872b64687f0b32003b0c7213854fd0",
        "course_id": 3,
        "id": 33182126,
        "seq": 28,
        "test_id": "area_15_03",
        "type": 1,
        "area": 15,
        "tigan": "关于风险和风险管理的描述，不正确的是（）",
        "A": "项目投入越多，愿意冒的风险就越小",
        "B": "最大的不确定性存在于项目的末期",
        "C": "投机风险在一定条件下可以转化为纯粹风险",
        "D": "项目风险管理的目的在于降低风险不利影响，提高项目成功的可能性",
        "answer": "B",
        "explanation": "P431，风险源于所有项目之中的不确定因素。项目在不同阶段会有不同的风险。风险会随着项目的进展而变化，不确定性也会着项目进展而逐渐减少。最大的不确定性存在于项目的早期。",
        "tigan_pic": "",
        "explanation_pic": "",
        "done_count": 128,
        "correct_count": 122,
        "correct_prob": 95.3,
        "fav_count": 2,
        "sim_questions": ""
      },
      {
        "_id": "c8872b64687f0b32003b0c6350747534",
        "course_id": 3,
        "id": 36551491,
        "seq": 29,
        "test_id": "area_15_03",
        "type": 1,
        "area": 15,
        "tigan": "关于风险的描述不正确的是（）。",
        "A": "项目风险管理过程是个持续的不断迭代的过程",
        "B": "风险包括对目标的威胁，也包括促进目标的机会",
        "C": "项目投入越大，可接受的风险越小",
        "D": "因灭火扑救、停工引发的成本属于直接风险损失",
        "answer": "D",
        "explanation": "P434，风险损失的有形成本包括风险事件造成的直接损失和间接损失。\n①直接损失。直接损失指财产损毁和人员伤亡的价值。如压缩空气机房在施工过程中失火。直接损失包括空压机的重置成本、受伤人员的医疗费、休养费、工资等。\n②间接损失。间接损失指直接损失以外的它物损失、责任损失以及因此而造成的收益的减少。包括因灭火扑救、停工等发生的成本。所以，因灭火扑救、停工引发的成本属于间接损失。",
        "tigan_pic": "",
        "explanation_pic": "",
        "done_count": 129,
        "correct_count": 125,
        "correct_prob": 96.9,
        "fav_count": 6,
        "sim_questions": ""
      },
      {
        "_id": "c8872b64687f0b32003b0c6a0865698b",
        "course_id": 3,
        "id": 37037206,
        "seq": 30,
        "test_id": "area_15_03",
        "type": 1,
        "area": 15,
        "tigan": "关于风险的描述，正确的是（）。",
        "A": "风险审计可以在日常项目审查中进行，也可以单独召开风险审计会议",
        "B": "蒙特卡洛分析有助于确定哪些风险对项目具有最大的潜在影响",
        "C": "风险的应对方案应该与风险的可管理性相匹配",
        "D": "建立应急储备，安排资金和资源应对风险是常见的规避风险策略",
        "answer": "A",
        "explanation": "P467，风险审计是一种审计类型，可用于评估风险管理过程的有效性。项目经理负责确保按项目风险管理计划所规定的频率开展风险审计。风险审计可以在日常项目审查会和风险审查会上开展，团队也可以召开专门的风险审计会。所以A正确，P455，敏感性分析有助于确定哪些风险对项目具有最大的潜在影响，所以B错误。P458，风险应对方案应该与风险的重要性相匹配，并且能够经济有效地应对挑战，同时在当前项目背景下现实可行，获得全体干系人的同意，并由一名责任人具体负责。所以C错误。P460，最常见的主动接受策略是建立应急储备，包括预留时间、资金或资源以应对出现的威胁。所以D错误",
        "tigan_pic": "",
        "explanation_pic": "",
        "done_count": 130,
        "correct_count": 81,
        "correct_prob": 62.3,
        "fav_count": 20,
        "sim_questions": ""
      }
    ]
  },
  "header": {
    "x-serverless-request-id": "ac1cc3171757657818753164572",
    "x-serverless-runtime-version": "2.1.3",
    "date": "Fri, 12 Sep 2025 06:16:58 GMT",
    "x-fc-invocation-function-version": "LATEST",
    "x-fc-instance-id": "c-68c3aed1-18797068-796859b4bf03",
    "x-fc-invocation-duration": "44",
    "x-fc-request-id": "1-68c3bada-18f48f71-90ec42a849bc",
    "transfer-encoding": "chunked",
    "content-type": "application/octet-stream",
    "x-fc-max-memory-usage": "37.70",
    "access-control-expose-headers": "Date,x-fc-request-id,x-fc-error-type,x-fc-code-checksum,x-fc-invocation-duration,x-fc-max-memory-usage,x-fc-log-result,x-fc-invocation-code-version,x-fc-instance-id",
    "x-fc-code-checksum": "3373688905125190371",
    "x-serverless-http-status": "200"
  }
}