{
  "success": true,
  "data": {
    "errCode": 0,
    "errMsg": "执行成功",
    "data": [
      {
        "_id": "c8872b64687f0b32003b08492379e2f1",
        "course_id": 3,
        "id": 34996673,
        "seq": 1,
        "test_id": "area_05_01",
        "type": 1,
        "area": 5,
        "tigan": "图中的软件架构设计属于()风格。",
        "A": "虚拟机风格",
        "B": "调用／返回风格",
        "C": "独立构件风格",
        "D": "数据流风格",
        "answer": "D",
        "explanation": "Garlan和Shaw 对通用软件架构风格进行了分类，他们将软件架构分为数据流风格、调用／返回风格、独立构件风格、虚拟机风格和仓库风格。\n1）数据流风格：包括批处理序列和管道／过滤器两种风格。\n2）调用／返回风格：包括主程序／子程序、数据抽象和面向对象，以及层次结构。\n3）独立构件风格：包括进程通信和事件驱动的系统。\n4）虚拟机风格：包括解释器和基于规则的系统。\n5）仓库风格：包括数据库系统、黑板系统和超文本系统。",
        "tigan_pic": "01_05_01.jpg",
        "explanation_pic": "",
        "done_count": 467,
        "correct_count": 351,
        "correct_prob": "75.2",
        "fav_count": 54,
        "sim_questions": ""
      },
      {
        "_id": "c8872b64687f0b32003b07fc73a0fb31",
        "course_id": 3,
        "id": 37699080,
        "seq": 2,
        "test_id": "area_05_01",
        "type": 1,
        "area": 5,
        "tigan": "在典型的软件架构模式中，()模式是基于资源不对等，为实现共享而提出的。",
        "A": "管道／过滤器",
        "B": "事件驱动",
        "C": "分层",
        "D": "客户机／服务器",
        "answer": "D",
        "explanation": "管道／过滤器模式：每个组件（过滤器）都有一组输入／输出，体现了各功能模块高内聚、低耦合的“黑盒”特性。\n事件驱动模式：其基本原理是组件并不直接调用操作，而是触发一个或多个事件。\n分层模式：采用层次化的组织方式，每一层都为上一层提供服务，并使用下一层提供的功能。\n客户机／服务器模式：基于资源不对等，为实现共享而提出的模式。",
        "tigan_pic": "",
        "explanation_pic": "",
        "done_count": 409,
        "correct_count": 262,
        "correct_prob": "64.1",
        "fav_count": 92,
        "sim_questions": ""
      },
      {
        "_id": "c8872b64687f0b32003b083f2b60e548",
        "course_id": 3,
        "id": 35842594,
        "seq": 3,
        "test_id": "area_05_01",
        "type": 1,
        "area": 5,
        "tigan": "（）反映企业或客户对系统高层次的目标要求，通常来自项目投资人、购买产品的客户等。",
        "A": "用户需求",
        "B": "业务需求",
        "C": "系统需求",
        "D": "企业需求",
        "answer": "B",
        "explanation": "①业务需求。业务需求是指反映企业或客户对系统高层次的目标要求，通常来自项目投资人、购买产品的客户、客户单位的管理人员、市场营销部门或产品策划部门等。通过业务需求可以确定项目视图和范围，项目视图和范围文档把业务需求集中在一个简单、紧凑的文档中，该文档为以后的开发工作奠定了基础。②用户需求。用户需求描述的是用户的具体目标，或用户要求系统必须能完成的任务。也就是说，用户需求描述了用户能使用系统来做些什么。通常采取用户访谈和问卷调查等方式，对用户使用的场景进行整理，从而建立用户需求。③系统需求。系统需求是从系统的角度来说明软件的需求，包括功能需求、非功能需求和设计约束等。功能需求也称为行为需求，它规定了开发人员必须在系统中实现的软件功能，用户利用这些功能来完成任务，满足业务需要。",
        "tigan_pic": "",
        "explanation_pic": "",
        "done_count": 405,
        "correct_count": 269,
        "correct_prob": "66.4",
        "fav_count": 69,
        "sim_questions": ""
      },
      {
        "_id": "c8872b64687f0b32003b081d68b5564d",
        "course_id": 3,
        "id": 33951548,
        "seq": 4,
        "test_id": "area_05_01",
        "type": 1,
        "area": 5,
        "tigan": "结构化分析模型包括功能模型、数据模型和行为模型。其中，功能模型用()来表示，描述信息流和数据从输入移动到输出的过程中所经受的加工／处理变换；数据模型用()来表示，描述数据对象、数据对象的属性及数据对象间的关系；行为模型用()来表示，描述系统或系统某个部分的状态以及引起状态转换的事件。",
        "A": "实体联系图 数据流图 状态转换图",
        "B": "数据流图 对象关系图 用例图",
        "C": "对象关系图 类图 用例图",
        "D": "数据流图 实体联系图 状态转换图",
        "answer": "D",
        "explanation": "结构化分析有三个层次的模型，分别是数据模型、功能模型和行为模型（也称为状态模型）。在实际工作中，一般使用实体联系图（E-R图）表示数据模型，用数据流图（DFD）表示功能模型，用状态转换图（STD）表示行为模型。",
        "tigan_pic": "",
        "explanation_pic": "",
        "done_count": 404,
        "correct_count": 244,
        "correct_prob": "60.4",
        "fav_count": 91,
        "sim_questions": ""
      },
      {
        "_id": "c8872b64687f0b32003b07fd27b9f51e",
        "course_id": 3,
        "id": 33489564,
        "seq": 5,
        "test_id": "area_05_01",
        "type": 1,
        "area": 5,
        "tigan": "结构化分析方法（SA）的主要思想是()。",
        "A": "自顶向下、逐步分解",
        "B": "自顶向下、逐步抽象",
        "C": "自底向上、逐步抽象",
        "D": "自底向上、逐步分解",
        "answer": "A",
        "explanation": "结构化分析方法（Structured Analysis，SA）是面向数据流进行需求分析的方法，采用自顶向下、逐步分解建立系统的处理流程，以数据流图和数据字典为主要工具，建立系统的逻辑模型。",
        "tigan_pic": "",
        "explanation_pic": "",
        "done_count": 409,
        "correct_count": 339,
        "correct_prob": "82.9",
        "fav_count": 27,
        "sim_questions": ""
      },
      {
        "_id": "c8872b64687f0b32003b082366df4137",
        "course_id": 3,
        "id": 36594558,
        "seq": 6,
        "test_id": "area_05_01",
        "type": 1,
        "area": 5,
        "tigan": "在面向对象的概念中，类是现实世界中实体的形式化描述，类将该实体的()和操作封装在一起。",
        "A": "属性",
        "B": "需求",
        "C": "对象",
        "D": "抽象",
        "answer": "A",
        "explanation": "类：现实世界中实体的形式化描述，类将该实体的属性（数据）和操作（函数）封装在一起。例如，Joe是一名教师，拥有教师的特征，这些特征就是教师这个类所具有的。\n类和对象的关系可理解为对象是类的实例，类是对象的模板。如果将对象比作房子，那么类就是房子的设计图纸。",
        "tigan_pic": "",
        "explanation_pic": "",
        "done_count": 465,
        "correct_count": 368,
        "correct_prob": "79.1",
        "fav_count": 44,
        "sim_questions": ""
      },
      {
        "_id": "c8872b64687f0b32003b0803387c6038",
        "course_id": 3,
        "id": 37123262,
        "seq": 7,
        "test_id": "area_05_01",
        "type": 1,
        "area": 5,
        "tigan": "结构化设计（SD）遵循一个基本的原则是()",
        "A": "低耦合、低内聚",
        "B": "高耦合、高内聚",
        "C": "高耦合、低内聚",
        "D": "低耦合、高内聚",
        "answer": "D",
        "explanation": "在SD中，需要遵循的一个基本原则：高内聚，低耦合。",
        "tigan_pic": "",
        "explanation_pic": "",
        "done_count": 417,
        "correct_count": 328,
        "correct_prob": "78.7",
        "fav_count": 21,
        "sim_questions": ""
      },
      {
        "_id": "c8872b64687f0b32003b08422785ec94",
        "course_id": 3,
        "id": 32743531,
        "seq": 8,
        "test_id": "area_05_01",
        "type": 1,
        "area": 5,
        "tigan": "面向对象设计的七大原则，不包括()",
        "A": "单职原则",
        "B": "迪米特原则",
        "C": "组合编码原则",
        "D": "李氏替换原则",
        "answer": "C",
        "explanation": "1）单职原则：设计功能单一的类。本原则与结构化方法的高内聚原则是一致的。\n2）开闭原则：对扩展开放，对修改封闭。\n3）李氏替换原则：子类可以替换父类。\n4）依赖倒置原则：要依赖于抽象，而不是具体实现；要针对接口编程，不要针对实现编程。\n5）接口隔离原则：使用多个专门的接口比使用单一的总接口要好。\n6）组合重用原则：要尽量使用组合，而不是继承关系达到重用目的。\n7）迪米特原则（最少知识法则）：一个对象应当对其他对象有尽可能少的了解。本原则与结构化方法的低耦合原则是一致的。",
        "tigan_pic": "",
        "explanation_pic": "",
        "done_count": 418,
        "correct_count": 245,
        "correct_prob": "58.6",
        "fav_count": 106,
        "sim_questions": ""
      },
      {
        "_id": "c8872b64687f0b32003b083967a94216",
        "course_id": 3,
        "id": 35140027,
        "seq": 9,
        "test_id": "area_05_01",
        "type": 1,
        "area": 5,
        "tigan": "下列()不是静态测试的方法。",
        "A": "黑盒测试",
        "B": "桌前检查",
        "C": "代码走查",
        "D": "代码审查",
        "answer": "A",
        "explanation": "静态测试包括桌前检查、代码走查和代码审查。动态测试一般采用白盒测试和黑盒测试方法。",
        "tigan_pic": "",
        "explanation_pic": "",
        "done_count": 421,
        "correct_count": 332,
        "correct_prob": "78.9",
        "fav_count": 47,
        "sim_questions": ""
      },
      {
        "_id": "c8872b64687f0b32003b08447512cf2b",
        "course_id": 3,
        "id": 37007700,
        "seq": 10,
        "test_id": "area_05_01",
        "type": 1,
        "area": 5,
        "tigan": "（）按照程序内部的结构测试程序，检验程序中的每条通路是否都能按预定要求正确工作，而不顾它的功能。",
        "A": "黑盒测试",
        "B": "白盒测试",
        "C": "代码审查",
        "D": "动态测试",
        "answer": "B",
        "explanation": "白盒测试也称结构测试或逻辑驱动测试，它是按照程序内部的结构测试程序，通过测试来检测产品内部动作是否按照设计规格说明书的规定正常进行，检验程序中的每条通路是否都能按预定要求正确工作。这一方法是把测试对象看作一个打开的盒子，测试人员依据程序内部逻辑结构相关信息，设计或选择测试用例，对程序所有逻辑路径进行测试，通过在不同点检查程序的状态，确定实际的状态是否与预期的状态一致。",
        "tigan_pic": "",
        "explanation_pic": "",
        "done_count": 421,
        "correct_count": 302,
        "correct_prob": "71.7",
        "fav_count": 66,
        "sim_questions": ""
      },
      {
        "_id": "c8872b64687f0b32003b07dc060ffa7c",
        "course_id": 3,
        "id": 30083642,
        "seq": 11,
        "test_id": "area_05_01",
        "type": 1,
        "area": 5,
        "tigan": "软件系统结构中各个模块间联系的紧密度是指()",
        "A": "内聚性",
        "B": "耦合性",
        "C": "层次性",
        "D": "关联性",
        "answer": "B",
        "explanation": "各模块间联系的紧密度是指耦合性。\n耦合性也叫块间联系。指软件系统结构中各模块间相互联系紧密程度的一种度量。模块之间联系越紧密，其耦合性就越强，模块之间越独立则耦合性越差，模块间耦合度的高低取决于模块间接口的复杂性，调用的方式以及传递的信息。\n内聚性又称块内联系，指模块的功能强度的度量，即一个模块内部各个元素彼此结合的紧密程度的度量。\n内聚性是对一个模块内部各个组成元素之间相互结合的紧密程度的度量指标。模块中组成元素结合得越紧密，模块的内聚性就越高，模块的独立性也就越高。理想的内聚性要求模块的功能明确单一，即一个模块只做一件事情。模块的内聚性和耦合性是两个相互对立且又密切相关的概念。",
        "tigan_pic": "",
        "explanation_pic": "",
        "done_count": 421,
        "correct_count": 333,
        "correct_prob": "79.1",
        "fav_count": 35,
        "sim_questions": ""
      },
      {
        "_id": "c8872b64687f0b32003b081e62654966",
        "course_id": 3,
        "id": 34464477,
        "seq": 12,
        "test_id": "area_05_01",
        "type": 1,
        "area": 5,
        "tigan": "软件测试是为评价和改进产品质量，识别产品的缺陷和问题而进行的活动，以下关于软件测试的叙述中，()是不正确的。",
        "A": "软件测试是软件开发中一个重要的环节",
        "B": "软件测试被认为是一种应该包括在整个开发和维护过程中的活动",
        "C": "软件测试是在有限测试用例集合上，静态验证软件是否达到预期的行为",
        "D": "软件测试是检查预防措施是否有效的主要手段，也是识别由于某种原因预防措施无效而产生错误的主要手段",
        "answer": "C",
        "explanation": "软件测试是一个系列过程活动，软件测试是针对一个程序的行为，在有限测试用例集合上，动态验证是否达到预期的行为，需要选取适当的测试用例。测试不仅是检测预防措施是否有效的主要手段，而且是识别由于某种原因预防措施无效而产生的错误的主要手段。",
        "tigan_pic": "",
        "explanation_pic": "",
        "done_count": 418,
        "correct_count": 364,
        "correct_prob": "87.1",
        "fav_count": 31,
        "sim_questions": ""
      },
      {
        "_id": "c8872b64687f0b32003b07e11f17f6f2",
        "course_id": 3,
        "id": 30235040,
        "seq": 13,
        "test_id": "area_05_01",
        "type": 1,
        "area": 5,
        "tigan": "用户想当然认为系统应具备的功能或性能，如果()没有得到实现，会让用户感到不满意。",
        "A": "期望需求",
        "B": "常规需求",
        "C": "软件需求",
        "D": "用户需求",
        "answer": "A",
        "explanation": "QFD将软件需求分为三类，分别是常规需求、期望需求和意外需求也要注意区分这些需求：\n1）常规需求。用户认为系统应该做到的功能或性能，实现越多用户会越满意。\n2）期望需求。用户想当然地认为系统应具备的功能或性能，但并不能正确描述自己想要得到的这些功能或性能需求。如果期望需求没有得到实现，会让用户感到不满意。\n3）意外需求。意外需求也称兴奋需求，是用户要求范围外的功能或性能（但通常是软件开发人员很乐意赋予系统的技术特性，实现这些需求用户会更高兴，但不实现也不影响购买的决策）。意外需求是控制在开发人员手中的，开发人员可以选择实现更多的意外需求，以便得到高满意度高忠诚度的用户，出于成本或项目周期的考虑，也可以选择不实现任何意外需求。",
        "tigan_pic": "",
        "explanation_pic": "",
        "done_count": 380,
        "correct_count": 276,
        "correct_prob": "72.6",
        "fav_count": 54,
        "sim_questions": ""
      },
      {
        "_id": "c8872b64687f0b32003b07fe526d74d8",
        "course_id": 3,
        "id": 38845316,
        "seq": 14,
        "test_id": "area_05_01",
        "type": 1,
        "area": 5,
        "tigan": "OOD是OOA方法的延续，其基本思想中的()主要通过继承和多态来实现。",
        "A": "抽象",
        "B": "封装",
        "C": "可扩展性",
        "D": "连续性",
        "answer": "C",
        "explanation": "面向对象设计（OOD）是OOA方法的延续，其基本思想包括抽象、封装和可扩展性，其中可扩展性主要通过继承和多态来实现。",
        "tigan_pic": "",
        "explanation_pic": "",
        "done_count": 415,
        "correct_count": 279,
        "correct_prob": "67.2",
        "fav_count": 78,
        "sim_questions": ""
      },
      {
        "_id": "c8872b64687f0b32003b08147ed86ec9",
        "course_id": 3,
        "id": 34357871,
        "seq": 15,
        "test_id": "area_05_01",
        "type": 1,
        "area": 5,
        "tigan": "（）是指用户在开发环境下进行测试。",
        "A": "Alpha测试",
        "B": "Beta 测试",
        "C": "用户测试",
        "D": "开发测试",
        "answer": "A",
        "explanation": "对于通用产品型的软件开发而言，Alpha 测试是指由用户在开发环境下进行测试，通过Alpha测试以后的产品通常称为Alpha版；Beta测试是指由用户在实际使用环境下进行测试，通过Beta测试的产品通常称为Beta版。一般在通过Beta测试后，才能把产品发布或交付给用户。",
        "tigan_pic": "",
        "explanation_pic": "",
        "done_count": 384,
        "correct_count": 231,
        "correct_prob": "60.2",
        "fav_count": 88,
        "sim_questions": ""
      },
      {
        "_id": "c8872b64687f0b32003b084b1a09cc99",
        "course_id": 3,
        "id": 37971956,
        "seq": 16,
        "test_id": "area_05_01",
        "type": 1,
        "area": 5,
        "tigan": "关于数据模型的说法，错误的是()",
        "A": "概念模型是按用户的观点来对数据和信息建模",
        "B": "关系模型由关系数据结构、关系操作集合和关系完整性约束三部分组成",
        "C": "逻辑模型是在关系模型的基础上确定模型的数据结构",
        "D": "物理数据模型是进行数据库体系结构设计，真正实现数据在数据库中的存放",
        "answer": "C",
        "explanation": "概念模型也称信息模型，它是按用户的观点来对数据和信息建模，把现实世界中的客观对象抽象为某一种平台无关的信息结构。\n逻辑模型是在概念模型的基础上确定模型的数据结构，目前主要的数据结构有层次模型、网状模型、关系模型、面向对象模型和对象关系模型。\n关系模型由关系数据结构、关系操作集合和关系完整性约束三部分组成。",
        "tigan_pic": "",
        "explanation_pic": "",
        "done_count": 377,
        "correct_count": 195,
        "correct_prob": "51.7",
        "fav_count": 122,
        "sim_questions": ""
      },
      {
        "_id": "c8872b64687f0b32003b083646816a4e",
        "course_id": 3,
        "id": 34073340,
        "seq": 17,
        "test_id": "area_05_01",
        "type": 1,
        "area": 5,
        "tigan": "（）的任务就是将概念模型中实体、属性和关联转换为关系模型结构中的关系模式。",
        "A": "关系模型设计",
        "B": "信息模型设计",
        "C": "逻辑模型设计",
        "D": "物理模型设计",
        "answer": "C",
        "explanation": "概念模型设计：把现实世界的具体需求抽象为信息世界的结构，将需求分析的结构抽象为概念模型的过程就是概念模型设计，其任务是确定实体和数据及其关联。\n逻辑模型设计：逻辑模型设计的任务就是将概念模型中实体、属性和关联转换为关系模型结构中的关系模式。\n物理模型设计：将数据模型转换为真正的数据库结构，考虑的主要问题包括命名、确定字段类型和编写必要的存储过程与触发器等。",
        "tigan_pic": "",
        "explanation_pic": "",
        "done_count": 423,
        "correct_count": 203,
        "correct_prob": "48.0",
        "fav_count": 99,
        "sim_questions": ""
      },
      {
        "_id": "c8872b64687f0b32003b07ea0492065b",
        "course_id": 3,
        "id": 35716968,
        "seq": 18,
        "test_id": "area_05_01",
        "type": 1,
        "area": 5,
        "tigan": "（）是数据库、文件和数据交换的基本数据单元，在特定的语义环境中被认为是不可再分的最小数据单元。",
        "A": "数据源",
        "B": "元数据",
        "C": "数据元",
        "D": "元组",
        "answer": "C",
        "explanation": "数据元是数据库、文件和数据交换的基本数据单元。数据库或文件由记录或元组等组成，而记录或元组则由数据元组成。在特定的语义环境中被认为是不可再分的最小数据单元。",
        "tigan_pic": "",
        "explanation_pic": "",
        "done_count": 382,
        "correct_count": 288,
        "correct_prob": "75.4",
        "fav_count": 51,
        "sim_questions": ""
      },
      {
        "_id": "c8872b64687f0b32003b08463ae9958d",
        "course_id": 3,
        "id": 37655131,
        "seq": 19,
        "test_id": "area_05_01",
        "type": 1,
        "area": 5,
        "tigan": "数据标准化阶段的具体过程为()\n①确定数据需求②建立数据模型 ③制定数据标准 ④批准数据标准 ⑤实施数据标准",
        "A": "①②③④⑤",
        "B": "②③④⑤",
        "C": "①③④⑤",
        "D": "②③④",
        "answer": "C",
        "explanation": "数据标准化阶段的具体过程包括确定数据需求、制定数据标准、批准数据标准和实施数据标准四个阶段。",
        "tigan_pic": "",
        "explanation_pic": "",
        "done_count": 418,
        "correct_count": 180,
        "correct_prob": "43.1",
        "fav_count": 121,
        "sim_questions": ""
      },
      {
        "_id": "c8872b64687f0b32003b08486a7742bc",
        "course_id": 3,
        "id": 31877616,
        "seq": 20,
        "test_id": "area_05_01",
        "type": 1,
        "area": 5,
        "tigan": "关于数据备份，目前常用的备份策略不包括()",
        "A": "完全备份",
        "B": "差异备份",
        "C": "增量备份",
        "D": "本地备份",
        "answer": "D",
        "explanation": "数据备份常见的备份策略主要有三种：完全备份、差分（差异）备份和增量备份。",
        "tigan_pic": "",
        "explanation_pic": "",
        "done_count": 422,
        "correct_count": 355,
        "correct_prob": "84.1",
        "fav_count": 34,
        "sim_questions": ""
      },
      {
        "_id": "c8872b64687f0b32003b081f646aa3d5",
        "course_id": 3,
        "id": 39354214,
        "seq": 21,
        "test_id": "area_05_01",
        "type": 1,
        "area": 5,
        "tigan": "下列关于数据库的安全说明中，不正确的是()",
        "A": "未获授权的用户有意或无意得到信息，不会对数据库安全造成威胁",
        "B": "非授权修改不一定会涉及非授权信息泄露，因为即使不读取数据也可以进行破坏",
        "C": "系统软硬件中的错误，可能导致非授权的信息泄露、数据修改或拒绝服务",
        "D": "病毒、特洛伊木马和后门威胁数据库安全",
        "answer": "A",
        "explanation": "数据库安全分类及说明见下表。",
        "tigan_pic": "",
        "explanation_pic": "01_05_02.jpg",
        "done_count": 381,
        "correct_count": 354,
        "correct_prob": "92.9",
        "fav_count": 23,
        "sim_questions": ""
      },
      {
        "_id": "c8872b64687f0b32003b07eb5ee69a87",
        "course_id": 3,
        "id": 31126197,
        "seq": 22,
        "test_id": "area_05_01",
        "type": 1,
        "area": 5,
        "tigan": "题目系统集成在技术上需要遵循的基本原则不包括（）",
        "A": "开放性",
        "B": "创造性",
        "C": "先进性",
        "D": "主流化",
        "answer": "B",
        "explanation": "系统集成的内容包括技术环境的集成、数据环境的集成和应用程序的集成。\n在技术上需要遵循的基本原则包括开放性、结构化、先进性和主流化。",
        "tigan_pic": "",
        "explanation_pic": "",
        "done_count": 415,
        "correct_count": 208,
        "correct_prob": "50.1",
        "fav_count": 80,
        "sim_questions": ""
      },
      {
        "_id": "c8872b64687f0b32003b08204b8bae89",
        "course_id": 3,
        "id": 35968208,
        "seq": 23,
        "test_id": "area_05_01",
        "type": 1,
        "area": 5,
        "tigan": "关于系统集成的说法，错误的是（）",
        "A": "企业中各分散业务子系统中的数据提取到企业数字化统一平台上，体现了数据集成",
        "B": "应用集成是将不同应用程序之间的功能集成到一个统一的应用中",
        "C": "网络集成是系统集成的硬件基础，为数字企业系统提供了一个网络运行平台",
        "D": "软件集成指将独立的软件应用连接起来，实现协同工作",
        "answer": "D",
        "explanation": "应用集成或组织应用集成（EAI）是指将独立的软件应用连接起来，实现协同工作。",
        "tigan_pic": "",
        "explanation_pic": "",
        "done_count": 387,
        "correct_count": 170,
        "correct_prob": "43.9",
        "fav_count": 130,
        "sim_questions": ""
      },
      {
        "_id": "c8872b64687f0b32003b07e268b86cef",
        "course_id": 3,
        "id": 38222039,
        "seq": 24,
        "test_id": "area_05_01",
        "type": 1,
        "area": 5,
        "tigan": "平台的安全操作系统、安全数据库、应用开发运营的安全平台以及网络安全管理监控系统等，体现了信息安全系统三维空间中的",
        "A": "安全机制",
        "B": "安全服务",
        "C": "OSI网络参考模型",
        "D": "安全技术",
        "answer": "A",
        "explanation": "X轴（安全机制）：为提供某些安全服务，利用各种安全技术和技巧所形成的一个较为完善的结构体系。如平台安全机制，主要指安全操作系统、安全数据库、应用开发运营的安全平台以及网络安全管理监控系统等。\nY轴（OSI网络参考模型）：信息安全系统的许多技术、技巧都是在网络的各个层面上实施的，离开网络，信息系统的安全也就失去了意义。\nZ轴（安全服务）：就是从网络中的各个层面提供给信息应用系统所需要的安全服务支持。如对等实体认证服务、访问控制服务、数据保密服务等。",
        "tigan_pic": "",
        "explanation_pic": "",
        "done_count": 422,
        "correct_count": 266,
        "correct_prob": "63.0",
        "fav_count": 98,
        "sim_questions": ""
      },
      {
        "_id": "c8872b64687f0b32003b07ff1dd7d232",
        "course_id": 3,
        "id": 35236196,
        "seq": 25,
        "test_id": "area_05_01",
        "type": 1,
        "area": 5,
        "tigan": "在信息安全系统工程中，（）用以防止数据被篡改、插入、删除以及丢失。",
        "A": "数据保密服务",
        "B": "数据完整性服务",
        "C": "数字签名",
        "D": "访问控制",
        "answer": "B",
        "explanation": "数据保密服务：包括多种保密服务，为了防止网络中各系统之间的数据被截获或被非法存取而泄密，提供密码加密保护。提供链接方式和无链接方式两种数据保密，同时也可对用户可选字段的数据进行保护。\n数据完整性服务：防止非法实体对交换数据进行修改、插入、删除及在数据交换过程中的丢失。",
        "tigan_pic": "",
        "explanation_pic": "",
        "done_count": 410,
        "correct_count": 258,
        "correct_prob": "62.9",
        "fav_count": 66,
        "sim_questions": ""
      }
    ]
  },
  "header": {
    "x-serverless-request-id": "ac1cc3181757656459901183266",
    "x-serverless-runtime-version": "2.1.3",
    "date": "Fri, 12 Sep 2025 05:54:20 GMT",
    "x-fc-invocation-function-version": "LATEST",
    "x-fc-instance-id": "c-68c3aed1-18797068-796859b4bf03",
    "x-fc-invocation-duration": "47",
    "x-fc-request-id": "1-68c3b58b-181eb8bd-8ffeb0904399",
    "transfer-encoding": "chunked",
    "content-type": "application/octet-stream",
    "x-fc-max-memory-usage": "36.38",
    "access-control-expose-headers": "Date,x-fc-request-id,x-fc-error-type,x-fc-code-checksum,x-fc-invocation-duration,x-fc-max-memory-usage,x-fc-log-result,x-fc-invocation-code-version,x-fc-instance-id",
    "x-fc-code-checksum": "3373688905125190371",
    "x-serverless-http-status": "200"
  }
}